Workbook

Sheet ACCUEIL
B3: 📦 SYSTÈME ERP — GESTION DES STOCKS
B4: Académie d'El Bayadh — Mahi Kamel Abdelghani
B5: Version 3.0 — Mars 2026 | Bugs EOQ corrigés + CMUP dynamique + ROP Dashboard
B7: Onglet | C7: Description
B8: 📋 ARTICLES | C8: Catalogue de tous les articles du magasin
B9: 📊 FOURNISSEURS | C9: Fiches et évaluations des fournisseurs
B10: 🔄 MOUVEMENTS | C10: Entrées et sorties de stock
B11: 📈 DASHBOARD | C11: Tableau de bord — alertes stock
B12: 🧮 INVENTAIRE | C12: Fiche de stock CMUP + valorisation
B13: 📐 CALCULS_EOQ | C13: Paramètres Wilson + point de commande
B14: 📁 HISTORIQUE | C14: Archivage des commandes et réceptions
B15: ℹ️ GUIDE | C15: Instructions d'utilisation détaillées
B17: ⚠️ Activer les macros si demandé | Ne pas modifier les formules | Sauvegarder régulièrement

Sheet ARTICLES
A1: 📋 CATALOGUE DES ARTICLES — MAGASIN ACADÉMIE EL BAYADH
A2: Code Article | B2: Désignation | C2: Catégorie | D2: Classe ABC | E2: Unité | F2: Stock Minimum | G2: Stock Maximum | H2: Prix Unitaire (DA) | I2: Fournisseur Habituel | J2: Emplacement | K2: Actif (O/N)
A3: ART-001 | B3: Rame papier A4 80g/m² | C3: Papeterie | D3: C | E3: Rame | F3: 400 | G3: 1500 | H3: 180 | I3: Papeterie ENAP Alger | J3: Rayon A-E1 | K3: O
A4: ART-002 | B4: Cartouche toner laser noir HP | C4: Consommables | D4: A | E4: Unité | F4: 5 | G4: 30 | H4: 3500 | I4: Bureautique Center Oran | J4: Rayon B-E2 | K4: O
A5: ART-003 | B5: Cartouche encre couleur Canon | C5: Consommables | D5: A | E5: Unité | F5: 4 | G5: 20 | H5: 2200 | I5: Bureautique Center Oran | J5: Rayon B-E2 | K5: O
A6: ART-004 | B6: Stylo à bille bleu (boîte 50) | C6: Papeterie | D6: C | E6: Boîte | F6: 2 | G6: 15 | H6: 450 | I6: Papeterie ENAP Alger | J6: Rayon A-E1 | K6: O
A7: ART-005 | B7: Cahier 192 pages | C7: Papeterie | D7: C | E7: Unité | F7: 50 | G7: 500 | H7: 80 | I7: Papeterie ENAP Alger | J7: Rayon A-E3 | K7: O
A8: ART-006 | B8: Agrafeuse de bureau | C8: Matériel | D8: B | E8: Unité | F8: 2 | G8: 10 | H8: 1200 | I8: Bureau Plus Alger | J8: Rayon C-E1 | K8: O
A9: ART-007 | B9: Boîte d'agrafes N°24 | C9: Fournitures | D9: C | E9: Boîte | F9: 5 | G9: 50 | H9: 120 | I9: Papeterie ENAP Alger | J9: Rayon A-E2 | K9: O
A10: ART-008 | B10: Chemise cartonnée (50 unités) | C10: Papeterie | D10: C | E10: Paquet | F10: 3 | G10: 20 | H10: 350 | I10: Papeterie ENAP Alger | J10: Rayon A-E1 | K10: O
A11: ART-009 | B11: Tableau blanc magnétique 60x90 | C11: Matériel | D11: B | E11: Unité | F11: 1 | G11: 5 | H11: 4500 | I11: Atyab Algérie | J11: Rayon C-E2 | K11: O
A12: ART-010 | B12: Marqueur tableau blanc (rouge) | C12: Papeterie | D12: C | E12: Unité | F12: 10 | G12: 100 | H12: 95 | I12: Papeterie ENAP Alger | J12: Rayon A-E2 | K12: O
A13: ART-011 | B13: Tambour / Drum cartouche HP | C13: Consommables | D13: A | E13: Unité | F13: 1 | G13: 5 | H13: 8500 | I13: Bureautique Center Oran | J13: Rayon B-E1 | K13: O
A14: ART-012 | B14: Ruban adhésif scotch 48mm | C14: Fournitures | D14: C | E14: Rouleau | F14: 5 | G14: 40 | H14: 65 | I14: Papeterie ENAP Alger | J14: Rayon A-E2 | K14: O
... A17: ART-015 | B17: Rame papier A3 80g/m² | C17: Papeterie | D17: B | E17: Rame | F17: 20 | G17: 200 | H17: 350 | I17: Papeterie ENAP Alger | J17: Rayon A-E1 | K17: O

Sheet FOURNISSEURS
A1: 📊 FICHES FOURNISSEURS — ÉVALUATION ET SÉLECTION
A2: ⚙️ PONDÉRATIONS — modifiables | F2: Poids Qualité | G2: Poids Prix | H2: Poids Délai | I2: Poids Cond.
F3: 4 | G3: 3 | H3: 1.5 | I3: 1.5
A4: 💡 Modifiez F3:I3 pour recalculer tous les scores
A5: Code | B5: Nom Fournisseur | C5: Ville | D5: Téléphone | E5: Famille Produits | F5: Note Qualité /10 | G5: Note Prix /10 | H5: Note Délai /10 | I5: Note Cond. /10 | J5: =F5*$F$3+G5*$G$3+H5*$H$3+I5*$I$3
A6: F001 | B6: Papeterie ENAP Alger | C6: Alger | D6: 023-XX-XX-XX | E6: Papeterie/Fournitures | F6: 8 | G6: 7 | H6: 7 | I6: 8 | J6: =F6*$F$3+G6*$G$3+H6*$H$3+I6*$I$3
A7: F002 | B7: Bureautique Center Oran | C7: Oran | D7: 041-XX-XX-XX | E7: Consommables imprimantes | F7: 9 | G7: 6 | H7: 6 | I7: 7 | J7: =F7*$F$3+G7*$G$3+H7*$H$3+I7*$I$3
A8: F003 | B8: Bureau Plus Alger | C8: Alger | D8: 023-YY-YY-YY | E8: Matériel de bureau | F8: 7 | G8: 7 | H8: 7 | I8: 8 | J8: =F8*$F$3+G8*$G$3+H8*$H$3+I8*$I$3
A9: F004 | B9: Atyab Algérie | C9: Alger | D9: 023-ZZ-ZZ-ZZ | E9: Mobilier/Matériel | F9: 7 | G9: 8 | H9: 6 | I9: 7 | J9: =F9*$F$3+G9*$G$3+H9*$H$3+I9*$I$3
A10: F005 | B10: Papeterie locale El Bayadh | C10: El Bayadh | D10: 049-XX-XX-XX | E10: Papeterie basique | F10: 6 | G10: 9 | H10: 9 | I10: 7 | J10: =F7*4+G7*3+H7*1.5+I7*1.5

Sheet MOUVEMENTS
A1: 🔄 REGISTRE DES MOUVEMENTS DE STOCK — ENTRÉES / SORTIES
A2: Date | B2: Code Article | C2: Désignation | D2: Type | E2: Quantité | F2: Prix Unitaire | G2: Valeur (DA) | H2: N° Référence | I2: Opérateur | J2: Observations
A3: 46054 | B3: ART-001 | C3: =IFERROR(VLOOKUP(B3,ARTICLES!A:B,2,FALSE),"") | D3: IN | E3: 1000 | F3: 180 | G3: =E3*F3 | H3: BR-001 | I3: Mahi K. | J3: Stock initial
A4: 46054 | B4: ART-002 | C4: =IFERROR(VLOOKUP(B4,ARTICLES!A:B,2,FALSE),"") | D4: IN | E4: 10 | F4: 3500 | G4: =E4*F4 | H4: BR-001 | I4: Mahi K. | J4: Stock initial
A5: 46054 | B5: ART-003 | C5: =IFERROR(VLOOKUP(B5,ARTICLES!A:B,2,FALSE),"") | D5: IN | E5: 8 | F5: 2200 | G5: =E5*F5 | H5: BR-001 | I5: Mahi K. | J5: Stock initial
A6: 46058 | B6: ART-001 | C6: =IFERROR(VLOOKUP(B6,ARTICLES!A:B,2,FALSE),"") | D6: OUT | E6: 50 | F6: 180 | G6: =E6*F6 | H6: BS-001 | I6: Mahi K. | J6: Distribution lycée A
A7: 46061 | B7: ART-005 | C7: =IFERROR(VLOOKUP(B7,ARTICLES!A:B,2,FALSE),"") | D7: IN | E7: 200 | F7: 80 | G7: =E7*F7 | H7: BR-002 | I7: Mahi K. | J7: Commande mensuelle
A8: 46063 | B8: ART-002 | C8: =IFERROR(VLOOKUP(B8,ARTICLES!A:B,2,FALSE),"") | D8: OUT | E8: 2 | F8: 3500 | G8: =E8*F8 | H8: BS-002 | I8: Mahi K. | J8: Remplacement imprimante
A9: 46065 | B9: ART-001 | C9: =IFERROR(VLOOKUP(B9,ARTICLES!A:B,2,FALSE),"") | D9: OUT | E9: 100 | F9: 180 | G9: =E9*F9 | H9: BS-003 | I9: Mahi K. | J9: Distribution CEM B
A10: 46068 | B10: ART-004 | C10: =IFERROR(VLOOKUP(B10,ARTICLES!A:B,2,FALSE),"") | D10: IN | E10: 5 | F10: 450 | G10: =E10*F10 | H10: BR-003 | I10: Mahi K. | J10: Commande papeterie
A11: 46071 | B11: ART-011 | C11: =IFERROR(VLOOKUP(B11,ARTICLES!A:B,2,FALSE),"") | D11: OUT | E11: 1 | F11: 8500 | G11: =E11*F11 | H11: BS-004 | I11: Mahi K. | J11: Remplacement drum lycée
A12: 46073 | B12: ART-001 | C12: =IFERROR(VLOOKUP(B12,ARTICLES!A:B,2,FALSE),"") | D12: OUT | E12: 80 | F12: 180 | G12: =E12*F12 | H12: BS-005 | I12: Mahi K. | J12: Distribution lycée C
A13: 46082 | B13: ART-001 | C13: =IFERROR(VLOOKUP(B13,ARTICLES!A:B,2,FALSE),"") | D13: IN | E13: 500 | F13: 183 | G13: =E13*F13 | H13: BR-004 | I13: Mahi K. | J13: Réapprovisionnement
A14: 46086 | B14: ART-002 | C14: =IFERROR(VLOOKUP(B14,ARTICLES!A:B,2,FALSE),"") | D14: IN | E14: 8 | F14: 3500 | G14: =E14*F14 | H14: BR-005 | I14: Mahi K. | J14: Commande trimestrielle
... A17: 46096 | B17: ART-015 | C17: =IFERROR(VLOOKUP(B17,ARTICLES!A:B,2,FALSE),"") | D17: IN | E17: 50 | F17: 350 | G17: =E17*F17 | H17: BR-006 | I17: Mahi K. | J17: Commande A3
C18: =IFERROR(VLOOKUP(B18,ARTICLES!A:B,2,FALSE),"") | G18: =IF(E18="","",E18*F18)
C19: =IFERROR(VLOOKUP(B19,ARTICLES!A:B,2,FALSE),"") | G19: =IF(E19="","",E19*F19)
C20: =IFERROR(VLOOKUP(B20,ARTICLES!A:B,2,FALSE),"") | G20: =IF(E20="","",E20*F20)
C21: =IFERROR(VLOOKUP(B21,ARTICLES!A:B,2,FALSE),"") | G21: =IF(E21="","",E21*F21)
C22: =IFERROR(VLOOKUP(B22,ARTICLES!A:B,2,FALSE),"") | G22: =IF(E22="","",E22*F22)
C23: =IFERROR(VLOOKUP(B23,ARTICLES!A:B,2,FALSE),"") | G23: =IF(E23="","",E23*F23)
C24: =IFERROR(VLOOKUP(B24,ARTICLES!A:B,2,FALSE),"") | G24: =IF(E24="","",E24*F24)
C25: =IFERROR(VLOOKUP(B25,ARTICLES!A:B,2,FALSE),"") | G25: =IF(E25="","",E25*F25)
C26: =IFERROR(VLOOKUP(B26,ARTICLES!A:B,2,FALSE),"") | G26: =IF(E26="","",E26*F26)
C27: =IFERROR(VLOOKUP(B27,ARTICLES!A:B,2,FALSE),"") | G27: =IF(E27="","",E27*F27)
C28: =IFERROR(VLOOKUP(B28,ARTICLES!A:B,2,FALSE),"") | G28: =IF(E28="","",E28*F28)
C29: =IFERROR(VLOOKUP(B29,ARTICLES!A:B,2,FALSE),"") | G29: =IF(E29="","",E29*F29)
... C199: =IFERROR(VLOOKUP(B199,ARTICLES!A:B,2,FALSE),"") | G199: =IF(E199="","",E199*F199)

Sheet DASHBOARD
A1: 📈 TABLEAU DE BORD — ÉTAT DU STOCK EN TEMPS RÉEL
A2: Code Article | B2: Désignation | C2: Classe ABC | D2: Total Entrées | E2: Total Sorties | F2: Stock Actuel | G2: Stock Minimum | H2: Statut | I2: Conso/jour | J2: ROP (seuil commande) | K2: Jours restants
A3: ART-001 | B3: =IFERROR(VLOOKUP(A3,ARTICLES!A:B,2,FALSE),"") | C3: =IFERROR(VLOOKUP(A3,ARTICLES!A:D,4,FALSE),"") | D3: =SUMIFS(MOUVEMENTS!E:E,MOUVEMENTS!B:B,A3,MOUVEMENTS!D:D,"IN") | E3: =SUMIFS(MOUVEMENTS!E:E,MOUVEMENTS!B:B,A3,MOUVEMENTS!D:D,"OUT") | F3: =D3-E3 | G3: =IFERROR(VLOOKUP(A3,ARTICLES!A:F,6,FALSE),"") | H3: =IF(F3<=0,"🔴 RUPTURE",IF(F3<=J3,"⚠️ COMMANDER",IF(F3<=G3,"🟡 ALERTE","🟢 OK"))) | I3: =IFERROR(ROUND(E3/MAX(1,DAYS(TODAY(),DATE(2026,2,1))),2),0) | J3: =IFERROR(ROUND(I3*2+G3,0),G3) | K3: =IFERROR(IF(I3=0,"inf",ROUND(F3/I3,0)),"inf")
A4: ART-002 | B4: =IFERROR(VLOOKUP(A4,ARTICLES!A:B,2,FALSE),"") | C4: =IFERROR(VLOOKUP(A4,ARTICLES!A:D,4,FALSE),"") | D4: =SUMIFS(MOUVEMENTS!E:E,MOUVEMENTS!B:B,A4,MOUVEMENTS!D:D,"IN") | E4: =SUMIFS(MOUVEMENTS!E:E,MOUVEMENTS!B:B,A4,MOUVEMENTS!D:D,"OUT") | F4: =D4-E4 | G4: =IFERROR(VLOOKUP(A4,ARTICLES!A:F,6,FALSE),"") | H4: =IF(F4<=0,"🔴 RUPTURE",IF(F4<=J4,"⚠️ COMMANDER",IF(F4<=G4,"🟡 ALERTE","🟢 OK"))) | I4: =IFERROR(ROUND(E4/MAX(1,DAYS(TODAY(),DATE(2026,2,1))),2),0) | J4: =IFERROR(ROUND(I4*2+G4,0),G4) | K4: =IFERROR(IF(I4=0,"inf",ROUND(F4/I4,0)),"inf")
A5: ART-003 | B5: =IFERROR(VLOOKUP(A5,ARTICLES!A:B,2,FALSE),"") | C5: =IFERROR(VLOOKUP(A5,ARTICLES!A:D,4,FALSE),"") | D5: =SUMIFS(MOUVEMENTS!E:E,MOUVEMENTS!B:B,A5,MOUVEMENTS!D:D,"IN") | E5: =SUMIFS(MOUVEMENTS!E:E,MOUVEMENTS!B:B,A5,MOUVEMENTS!D:D,"OUT") | F5: =D5-E5 | G5: =IFERROR(VLOOKUP(A5,ARTICLES!A:F,6,FALSE),"") | H5: =IF(F5<=0,"🔴 RUPTURE",IF(F5<=J5,"⚠️ COMMANDER",IF(F5<=G5,"🟡 ALERTE","🟢 OK"))) | I5: =IFERROR(ROUND(E5/MAX(1,DAYS(TODAY(),DATE(2026,2,1))),2),0) | J5: =IFERROR(ROUND(I5*2+G5,0),G5) | K5: =IFERROR(IF(I5=0,"inf",ROUND(F5/I5,0)),"inf")
A6: ART-004 | B6: =IFERROR(VLOOKUP(A6,ARTICLES!A:B,2,FALSE),"") | C6: =IFERROR(VLOOKUP(A6,ARTICLES!A:D,4,FALSE),"") | D6: =SUMIFS(MOUVEMENTS!E:E,MOUVEMENTS!B:B,A6,MOUVEMENTS!D:D,"IN") | E6: =SUMIFS(MOUVEMENTS!E:E,MOUVEMENTS!B:B,A6,MOUVEMENTS!D:D,"OUT") | F6: =D6-E6 | G6: =IFERROR(VLOOKUP(A6,ARTICLES!A:F,6,FALSE),"") | H6: =IF(F6<=0,"🔴 RUPTURE",IF(F6<=J6,"⚠️ COMMANDER",IF(F6<=G6,"🟡 ALERTE","🟢 OK"))) | I6: =IFERROR(ROUND(E6/MAX(1,DAYS(TODAY(),DATE(2026,2,1))),2),0) | J6: =IFERROR(ROUND(I6*2+G6,0),G6) | K6: =IFERROR(IF(I6=0,"inf",ROUND(F6/I6,0)),"inf")
A7: ART-005 | B7: =IFERROR(VLOOKUP(A7,ARTICLES!A:B,2,FALSE),"") | C7: =IFERROR(VLOOKUP(A7,ARTICLES!A:D,4,FALSE),"") | D7: =SUMIFS(MOUVEMENTS!E:E,MOUVEMENTS!B:B,A7,MOUVEMENTS!D:D,"IN") | E7: =SUMIFS(MOUVEMENTS!E:E,MOUVEMENTS!B:B,A7,MOUVEMENTS!D:D,"OUT") | F7: =D7-E7 | G7: =IFERROR(VLOOKUP(A7,ARTICLES!A:F,6,FALSE),"") | H7: =IF(F7<=0,"🔴 RUPTURE",IF(F7<=J7,"⚠️ COMMANDER",IF(F7<=G7,"🟡 ALERTE","🟢 OK"))) | I7: =IFERROR(ROUND(E7/MAX(1,DAYS(TODAY(),DATE(2026,2,1))),2),0) | J7: =IFERROR(ROUND(I7*2+G7,0),G7) | K7: =IFERROR(IF(I7=0,"inf",ROUND(F7/I7,0)),"inf")
A8: ART-006 | B8: =IFERROR(VLOOKUP(A8,ARTICLES!A:B,2,FALSE),"") | C8: =IFERROR(VLOOKUP(A8,ARTICLES!A:D,4,FALSE),"") | D8: =SUMIFS(MOUVEMENTS!E:E,MOUVEMENTS!B:B,A8,MOUVEMENTS!D:D,"IN") | E8: =SUMIFS(MOUVEMENTS!E:E,MOUVEMENTS!B:B,A8,MOUVEMENTS!D:D,"OUT") | F8: =D8-E8 | G8: =IFERROR(VLOOKUP(A8,ARTICLES!A:F,6,FALSE),"") | H8: =IF(F8<=0,"🔴 RUPTURE",IF(F8<=J8,"⚠️ COMMANDER",IF(F8<=G8,"🟡 ALERTE","🟢 OK"))) | I8: =IFERROR(ROUND(E8/MAX(1,DAYS(TODAY(),DATE(2026,2,1))),2),0) | J8: =IFERROR(ROUND(I8*2+G8,0),G8) | K8: =IFERROR(IF(I8=0,"inf",ROUND(F8/I8,0)),"inf")
A9: ART-007 | B9: =IFERROR(VLOOKUP(A9,ARTICLES!A:B,2,FALSE),"") | C9: =IFERROR(VLOOKUP(A9,ARTICLES!A:D,4,FALSE),"") | D9: =SUMIFS(MOUVEMENTS!E:E,MOUVEMENTS!B:B,A9,MOUVEMENTS!D:D,"IN") | E9: =SUMIFS(MOUVEMENTS!E:E,MOUVEMENTS!B:B,A9,MOUVEMENTS!D:D,"OUT") | F9: =D9-E9 | G9: =IFERROR(VLOOKUP(A9,ARTICLES!A:F,6,FALSE),"") | H9: =IF(F9<=0,"🔴 RUPTURE",IF(F9<=J9,"⚠️ COMMANDER",IF(F9<=G9,"🟡 ALERTE","🟢 OK"))) | I9: =IFERROR(ROUND(E9/MAX(1,DAYS(TODAY(),DATE(2026,2,1))),2),0) | J9: =IFERROR(ROUND(I9*2+G9,0),G9) | K9: =IFERROR(IF(I9=0,"inf",ROUND(F9/I9,0)),"inf")
A10: ART-008 | B10: =IFERROR(VLOOKUP(A10,ARTICLES!A:B,2,FALSE),"") | C10: =IFERROR(VLOOKUP(A10,ARTICLES!A:D,4,FALSE),"") | D10: =SUMIFS(MOUVEMENTS!E:E,MOUVEMENTS!B:B,A10,MOUVEMENTS!D:D,"IN") | E10: =SUMIFS(MOUVEMENTS!E:E,MOUVEMENTS!B:B,A10,MOUVEMENTS!D:D,"OUT") | F10: =D10-E10 | G10: =IFERROR(VLOOKUP(A10,ARTICLES!A:F,6,FALSE),"") | H10: =IF(F10<=0,"🔴 RUPTURE",IF(F10<=J10,"⚠️ COMMANDER",IF(F10<=G10,"🟡 ALERTE","🟢 OK"))) | I10: =IFERROR(ROUND(E10/MAX(1,DAYS(TODAY(),DATE(2026,2,1))),2),0) | J10: =IFERROR(ROUND(I10*2+G10,0),G10) | K10: =IFERROR(IF(I10=0,"inf",ROUND(F10/I10,0)),"inf")
A11: ART-009 | B11: =IFERROR(VLOOKUP(A11,ARTICLES!A:B,2,FALSE),"") | C11: =IFERROR(VLOOKUP(A11,ARTICLES!A:D,4,FALSE),"") | D11: =SUMIFS(MOUVEMENTS!E:E,MOUVEMENTS!B:B,A11,MOUVEMENTS!D:D,"IN") | E11: =SUMIFS(MOUVEMENTS!E:E,MOUVEMENTS!B:B,A11,MOUVEMENTS!D:D,"OUT") | F11: =D11-E11 | G11: =IFERROR(VLOOKUP(A11,ARTICLES!A:F,6,FALSE),"") | H11: =IF(F11<=0,"🔴 RUPTURE",IF(F11<=J11,"⚠️ COMMANDER",IF(F11<=G11,"🟡 ALERTE","🟢 OK"))) | I11: =IFERROR(ROUND(E11/MAX(1,DAYS(TODAY(),DATE(2026,2,1))),2),0) | J11: =IFERROR(ROUND(I11*2+G11,0),G11) | K11: =IFERROR(IF(I11=0,"inf",ROUND(F11/I11,0)),"inf")
A12: ART-010 | B12: =IFERROR(VLOOKUP(A12,ARTICLES!A:B,2,FALSE),"") | C12: =IFERROR(VLOOKUP(A12,ARTICLES!A:D,4,FALSE),"") | D12: =SUMIFS(MOUVEMENTS!E:E,MOUVEMENTS!B:B,A12,MOUVEMENTS!D:D,"IN") | E12: =SUMIFS(MOUVEMENTS!E:E,MOUVEMENTS!B:B,A12,MOUVEMENTS!D:D,"OUT") | F12: =D12-E12 | G12: =IFERROR(VLOOKUP(A12,ARTICLES!A:F,6,FALSE),"") | H12: =IF(F12<=0,"🔴 RUPTURE",IF(F12<=J12,"⚠️ COMMANDER",IF(F12<=G12,"🟡 ALERTE","🟢 OK"))) | I12: =IFERROR(ROUND(E12/MAX(1,DAYS(TODAY(),DATE(2026,2,1))),2),0) | J12: =IFERROR(ROUND(I12*2+G12,0),G12) | K12: =IFERROR(IF(I12=0,"inf",ROUND(F12/I12,0)),"inf")
A13: ART-011 | B13: =IFERROR(VLOOKUP(A13,ARTICLES!A:B,2,FALSE),"") | C13: =IFERROR(VLOOKUP(A13,ARTICLES!A:D,4,FALSE),"") | D13: =SUMIFS(MOUVEMENTS!E:E,MOUVEMENTS!B:B,A13,MOUVEMENTS!D:D,"IN") | E13: =SUMIFS(MOUVEMENTS!E:E,MOUVEMENTS!B:B,A13,MOUVEMENTS!D:D,"OUT") | F13: =D13-E13 | G13: =IFERROR(VLOOKUP(A13,ARTICLES!A:F,6,FALSE),"") | H13: =IF(F13<=0,"🔴 RUPTURE",IF(F13<=J13,"⚠️ COMMANDER",IF(F13<=G13,"🟡 ALERTE","🟢 OK"))) | I13: =IFERROR(ROUND(E13/MAX(1,DAYS(TODAY(),DATE(2026,2,1))),2),0) | J13: =IFERROR(ROUND(I13*2+G13,0),G13) | K13: =IFERROR(IF(I13=0,"inf",ROUND(F13/I13,0)),"inf")
A14: ART-012 | B14: =IFERROR(VLOOKUP(A14,ARTICLES!A:B,2,FALSE),"") | C14: =IFERROR(VLOOKUP(A14,ARTICLES!A:D,4,FALSE),"") | D14: =SUMIFS(MOUVEMENTS!E:E,MOUVEMENTS!B:B,A14,MOUVEMENTS!D:D,"IN") | E14: =SUMIFS(MOUVEMENTS!E:E,MOUVEMENTS!B:B,A14,MOUVEMENTS!D:D,"OUT") | F14: =D14-E14 | G14: =IFERROR(VLOOKUP(A14,ARTICLES!A:F,6,FALSE),"") | H14: =IF(F14<=0,"🔴 RUPTURE",IF(F14<=J14,"⚠️ COMMANDER",IF(F14<=G14,"🟡 ALERTE","🟢 OK"))) | I14: =IFERROR(ROUND(E14/MAX(1,DAYS(TODAY(),DATE(2026,2,1))),2),0) | J14: =IFERROR(ROUND(I14*2+G14,0),G14) | K14: =IFERROR(IF(I14=0,"inf",ROUND(F14/I14,0)),"inf")
... A17: ART-015 | B17: =IFERROR(VLOOKUP(A17,ARTICLES!A:B,2,FALSE),"") | C17: =IFERROR(VLOOKUP(A17,ARTICLES!A:D,4,FALSE),"") | D17: =SUMIFS(MOUVEMENTS!E:E,MOUVEMENTS!B:B,A17,MOUVEMENTS!D:D,"IN") | E17: =SUMIFS(MOUVEMENTS!E:E,MOUVEMENTS!B:B,A17,MOUVEMENTS!D:D,"OUT") | F17: =D17-E17 | G17: =IFERROR(VLOOKUP(A17,ARTICLES!A:F,6,FALSE),"") | H17: =IF(F17<=0,"🔴 RUPTURE",IF(F17<=J17,"⚠️ COMMANDER",IF(F17<=G17,"🟡 ALERTE","🟢 OK"))) | I17: =IFERROR(ROUND(E17/MAX(1,DAYS(TODAY(),DATE(2026,2,1))),2),0) | J17: =IFERROR(ROUND(I17*2+G17,0),G17) | K17: =IFERROR(IF(I17=0,"inf",ROUND(F17/I17,0)),"inf")
A19: RÉSUMÉ GLOBAL
A20: ⚙️ Lead Time utilisé dans ROP (col J) : | D20: 2 | E20: jours ← modifiez si nécessaire puis adaptez la formule de J3:J17
A21: Articles en ALERTE: | D21: =COUNTIF(H3:H17,"🟡 ALERTE")
A22: Articles en RUPTURE: | D22: =COUNTIF(H3:H17,"🔴 RUPTURE")
A23: Articles OK: | D23: =COUNTIF(H3:H17,"🟢 OK")

Sheet INVENTAIRE
A1: 🧮 FICHE CMUP — INVENTAIRE PERMANENT EN TEMPS RÉEL
A2: Article sélectionné : | D2: ART-001 | E2: ← Menu déroulant : choisissez un article
A3: Désignation : | D3: =IFERROR(VLOOKUP(D2,ARTICLES!A:B,2,FALSE),"— introuvable —") | I3: Seuil min : | J3: =IFERROR(VLOOKUP(D2,ARTICLES!A:F,6,FALSE),"") | K3: Classe ABC : | L3: =IFERROR(VLOOKUP(D2,ARTICLES!A:D,4,FALSE),"")
A4: 📊 INDICATEURS EN TEMPS RÉEL (mis à jour automatiquement)
A5: Total entrées (unités) | B5: Total sorties (unités) | C5: Stock actuel (unités) | D5: Valeur totale IN (DA) | E5: CMUP actuel (DA/unité) | F5: Stock valorisé (DA) | G5: Statut
A6: =SUMIFS(MOUVEMENTS!E:E,MOUVEMENTS!B:B,D2,MOUVEMENTS!D:D,"IN") | B6: =SUMIFS(MOUVEMENTS!E:E,MOUVEMENTS!B:B,D2,MOUVEMENTS!D:D,"OUT") | C6: =A6-B6 | D6: =IFERROR(SUMPRODUCT((MOUVEMENTS!B$3:B$200=D2)*(MOUVEMENTS!D$3:D$200="IN")*MOUVEMENTS!E$3:E$200*MOUVEMENTS!F$3:F$200),0) | E6: =IFERROR(D6/A6,IFERROR(VLOOKUP(D2,ARTICLES!A:H,8,FALSE),0)) | F6: =C6*E6 | G6: =IF(C6<=0,"🔴 RUPTURE",IF(C6<=IFERROR(VLOOKUP(D2,ARTICLES!A:F,6,FALSE),0),"🟡 ALERTE","🟢 OK"))
A8: 📝 COMMENT UTILISER CETTE FICHE
A9: 1. Changez le code en D2 (menu déroulant) → tous les indicateurs se recalculent automatiquement.
A10: 2. CMUP en E6 = Valeur totale des entrées / Quantité totale entrée (méthode CMUP après dernière entrée).
A11: 3. Pour voir le détail chronologique : filtrez la feuille MOUVEMENTS (colonne B = code article).
A12: 4. Valeur stock (F6) = Stock actuel × CMUP = valeur bilancielle pour le rapport d'inventaire.

Sheet CALCULS_EOQ
A1: 📐 PARAMÈTRES WILSON — QUANTITÉ ÉCONOMIQUE DE COMMANDE (EOQ)
A2: 🔵 PARAMÈTRES D'ENTRÉE (modifier les valeurs en bleu)
A3: D (Demande annuelle) | B3: 1000 | C3: rames | D3: Consommation annuelle totale en unités
A4: CL (Coût de passation) | B4: 50 | C4: DA/cmd | D4: Frais administratifs par commande passée
A5: PU (Prix unitaire) | B5: 180 | C5: DA/rame | D5: Prix d'achat moyen d'une rame A4
A6: t (Taux de possession) | B6: 0.2 | C6: % | D6: 20% = coût de stockage annuel/valeur
A7: SS (Stock de sécurité) | B7: 200 | C7: rames | D7: Tampon contre les délais fournisseurs
A8: DL (Délai de livraison) | B8: 2 | C8: semaines | D8: Délai fournisseur Alger → El Bayadh
A9: S (Semaines travaillées/an) | B9: 50 | C9: semaines | D9: Semaines effectives de consommation
A11: 🟢 RÉSULTATS CALCULÉS AUTOMATIQUEMENT
A12: EOQ — Quantité Économique | B12: =ROUND(SQRT(2*B3*B4/(B6*B5)),0) | C12: ← Source EOQ pour toutes les formules ci-dessous | D12: Lot optimal à commander
A13: N — Nb de commandes/an | B13: =IFERROR(ROUND(B3/B12,1),"") | C13: cmd/an | D13: Fréquence annuelle de commandes
A14: Conso. hebdomadaire | B14: =ROUND(B3/B9,0) | C14: rames/sem | D14: B3/B9 — consommation par semaine
A15: ROP — Point de commande | B15: =ROUND((B3/B9)*B8+B7,0) | C15: rames | D15: Déclencher commande à ce niveau
A16: Stock moyen détenu | B16: =IFERROR(ROUND(B12/2+B7,0),"") | C16: rames | D16: EOQ/2 + stock sécurité
A17: Coût annuel de passation | B17: =IFERROR(ROUND((B3/B12)*B4,0),"") | C17: DA | D17: Nb cmd × CL
A18: Coût annuel de détention | B18: =IFERROR(ROUND((B12/2+B7)*B6*B5,0),"") | C18: DA | D18: Stock moyen × t × PU
A19: Coût Variable Total (CVT) | B19: =IFERROR(B17+B18,"") | C19: ✅ Corrigé: CVT = Cp + Cd (était référence circulaire) | D19: Passation + Détention

Sheet HISTORIQUE
A1: 📁 HISTORIQUE DES COMMANDES ET RÉCEPTIONS
A2: N° BC | B2: Date BC | C2: Fournisseur | D2: Article | E2: Qté commandée | F2: Date livraison | G2: Qté reçue | H2: Statut BC
A3: BC-001 | B3: 2026-02-01 | C3: Papeterie ENAP Alger | D3: Rame papier A4 | E3: 1000 | F3: 2026-02-03 | G3: 1000 | H3: ✅ Livré
A4: BC-002 | B4: 2026-02-08 | C4: Papeterie ENAP Alger | D4: Cahier 192 pages | E4: 200 | F4: 2026-02-10 | G4: 200 | H4: ✅ Livré
A5: BC-003 | B5: 2026-02-15 | C5: Papeterie ENAP Alger | D5: Stylos boîte 50 | E5: 5 | F5: 2026-02-17 | G5: 5 | H5: ✅ Livré
A6: BC-004 | B6: 2026-03-01 | C6: Papeterie ENAP Alger | D6: Rame papier A4 | E6: 500 | F6: 2026-03-03 | G6: 500 | H6: ✅ Livré
A7: BC-005 | B7: 2026-03-05 | C7: Bureautique Center | D7: Cartouche toner HP | E7: 8 | F7: 2026-03-08 | G7: 8 | H7: ✅ Livré
A8: BC-006 | B8: 2026-03-15 | C8: Papeterie ENAP Alger | D8: Rame papier A3 | E8: 50 | F8: 2026-03-18 | G8: 50 | H8: ✅ Livré
A9: BC-007 | B9: 2026-03-20 | C9: Bureautique Center | D9: Tambour HP | E9: 1 | G9: 0 | H9: 🕐 En attente

Sheet GUIDE
B1: ℹ️ GUIDE D'UTILISATION — SYSTÈME ERP STOCK ACADÉMIE
B3: ACCUEIL & NAVIGATION
B4: Ce fichier est le système ERP de gestion des stocks du magasin de l'Académie d'El Bayadh.
B5: Chaque onglet correspond à un module. Ne jamais supprimer une colonne avec une formule.
B6: Sauvegarder une copie de sauvegarde chaque semaine (ex: ERP_Stock_2026_S12.xlsx).
B8: ARTICLES — Comment ajouter un article
B9: 1. Aller sur l'onglet ARTICLES.
B10: 2. Saisir le code article (ex: ART-016) dans la colonne A.
B11: 3. Remplir la désignation, catégorie, classe ABC (A/B/C), unité, stocks min/max, prix, fournisseur, emplacement.
B12: 4. Aller sur DASHBOARD et ajouter le même code article en colonne A pour l'activer.
B14: MOUVEMENTS — Enregistrer une entrée ou sortie
B15: 1. Aller sur l'onglet MOUVEMENTS.
... B48: Si Excel demande d'activer les macros, cliquer sur Activer.
