Workbook
Name Segment_PROUDUIT: #N/A
Name tablnom: [1]Feuil1!$M$2:$N$8

Sheet graphiques
B1: pour faire la mise en forme de cellules : | F1: 1- accueil 2- police
B3: janvier | C3: février | D3: mars | E3: avril | F3: mai | G3: juin | H3: juillet | I3: août | J3: septembre | K3: octobre | L3: novembre | M3: décembre
A4: recette recettte | B4: 50000 | C4: 70000 | D4: 90000 | E4: 110000 | F4: 130000 | G4: 150000 | H4: 170000 | I4: 190000 | J4: 210000 | K4: 230000 | L4: 250000 | M4: 270000
A5: dépense | B5: 35000 | C5: 40000 | D5: 45000 | E5: 50000 | F5: 55000 | G5: 60000 | H5: 65000 | I5: 70000 | J5: 75000 | K5: 80000 | L5: 85000 | M5: 90000
A6: solde | B6: =+B4-B5 -> 15000 | C6: =+C4-C5 -> 30000 | D6: =+D4-D5 -> 45000 | E6: =+E4-E5 -> 60000 | F6: =+F4-F5 -> 75000 | G6: =+G4-G5 -> 90000 | H6: =+H4-H5 -> 105000 | I6: =+I4-I5 -> 120000 | ... M6: =+M4-M5 -> 180000
B8: 1- collage spécial ; 2- transposé | I8: pour faire graphique : | K8: 1- insertion 2- graphique
B10: recette | C10: dépense | D10: solde
A11: janvier | B11: 150000 | C11: 35000 | D11: =+B11-C11 -> 115000
A12: février | B12: 70000 | C12: 40000 | D12: =+B12-C12 -> 30000
A13: mars | B13: 90000 | C13: 45000 | D13: =+B13-C13 -> 45000
A14: avril | B14: 110000 | C14: 50000 | D14: =+B14-C14 -> 60000
A15: mai | B15: 130000 | C15: 55000 | D15: =+B15-C15 -> 75000
A16: juin | B16: 150000 | C16: 60000 | D16: =+B16-C16 -> 90000
A17: juillet | B17: 170000 | C17: 65000 | D17: =+B17-C17 -> 105000
A18: août | B18: 190000 | C18: 70000 | D18: =+B18-C18 -> 120000
A19: septembre | B19: 210000 | C19: 75000 | D19: =+B19-C19 -> 135000
A20: octobre | B20: 230000 | C20: 80000 | D20: =+B20-C20 -> 150000
A21: novembre | B21: 250000 | C21: 85000 | D21: =+B21-C21 -> 165000
A22: décembre | B22: 270000 | C22: 90000 | D22: =+B22-C22 -> 180000

Sheet LES FORMULES BASIQUES
B1: recette | C1: dépense | D1: solde
A2: janvier | B2: 50000 | C2: 35000 | D2: =+B2-C2 -> 15000 | G2: =SUM(B2:B13) -> 1920000
A3: février | B3: 70000 | C3: 40000 | D3: =+B3-C3 -> 30000
A4: mars | B4: 90000 | C4: 45000 | D4: =+B4-C4 -> 45000
A5: avril | B5: 110000 | C5: 50000 | D5: =+B5-C5 -> 60000
A6: mai | B6: 130000 | C6: 55000 | D6: =+B6-C6 -> 75000
A7: juin | B7: 150000 | C7: 60000 | D7: =+B7-C7 -> 90000
A8: juillet | B8: 170000 | C8: 65000 | D8: =+B8-C8 -> 105000
A9: août | B9: 190000 | C9: 70000 | D9: =+B9-C9 -> 120000
A10: septembre | B10: 210000 | C10: 75000 | D10: =+B10-C10 -> 135000
A11: octobre | B11: 230000 | C11: 80000 | D11: =+B11-C11 -> 150000
A12: novembre | B12: 250000 | C12: 85000 | D12: =+B12-C12 -> 165000
A13: décembre | B13: 270000 | C13: 90000 | D13: =+B13-C13 -> 180000
A14: TOTAL | B14: =SUM(B2:B13) -> 1920000 | C14: =SUM(C2:C13) -> 750000 | D14: =SUM(D2:D13) -> 1170000 | F14: CALCULE TOTAL : | G14: UTILISE LA FORMULE SOMME
A15: NB | B15: =+COUNT(B2:B13) -> 12 | C15: =+COUNT(C2:C13) -> 12 | D15: =+COUNT(D2:D13) -> 12 | F15: CALCULE NB : | G15: UTILISE LA FORMULE NB
A16: MAX | B16: =+MAX(B2:B13) -> 270000 | C16: =+MAX(C2:C13) -> 90000 | D16: =+MAX(D2:D13) -> 180000 | F16: CALCULE MAX : | G16: UTILISE LA FORMULE MAX
A17: MIN | B17: =+MIN(B2:B13) -> 50000 | C17: =+MIN(C2:C13) -> 35000 | D17: =+MIN(D2:D13) -> 15000 | F17: CALCULE MIN : | G17: UTILISE LA FORMULE MIN
A18: MOYENNE | B18: =+AVERAGE(B2:B13) -> 160000 | C18: =+AVERAGE(C2:C13) -> 62500 | D18: =+AVERAGE(D2:D13) -> 97500 | F18: CALCULE MOYENNE : | G18: UTILISE LA FORMULE MOYENNE
A19: MOYENNE | B19: =+B14/B15 -> 160000 | C19: =+C14/C15 -> 62500 | D19: =+D14/D15 -> 97500 | F19: CALCULE MOYENNE : | G19: TOTAL / NB

Sheet format tableau 
A2: pou fair format tableau : | C2: PROUDUIT | D2: PU | E2: Q | F2: HT | G2: TVA | H2: TTC
A3: 1- insertion 2-tableau | C3: DELL | D3: 50000 | E3: 6 | F3: =+'format tableau '!$D3*'format tableau '!$E3 -> 300000 | G3: =+'format tableau '!$F3*0.19 -> 57000 | H3: =+'format tableau '!$F3+'format tableau '!$G3 -> 357000
C4: DELL | D4: 50000 | E4: 6 | F4: =+'format tableau '!$D4*'format tableau '!$E4 -> 300000 | G4: =+'format tableau '!$F4*0.19 -> 57000 | H4: =+'format tableau '!$F4+'format tableau '!$G4 -> 357000
C5: DELL | D5: 50000 | E5: 6 | F5: =+'format tableau '!$D5*'format tableau '!$E5 -> 300000 | G5: =+'format tableau '!$F5*0.19 -> 57000 | H5: =+'format tableau '!$F5+'format tableau '!$G5 -> 357000
A6: pour rechercher : | C6: DELL | D6: 50000 | E6: 6 | F6: =+'format tableau '!$D6*'format tableau '!$E6 -> 300000 | G6: =+'format tableau '!$F6*0.19 -> 57000 | H6: =+'format tableau '!$F6+'format tableau '!$G6 -> 357000
A7: 1- ctrl + f | C7: TELEPHONE | D7: 60000 | E7: 4 | F7: =+'format tableau '!$D7*'format tableau '!$E7 -> 240000 | G7: =+'format tableau '!$F7*0.19 -> 45600 | H7: =+'format tableau '!$F7+'format tableau '!$G7 -> 285600
C8: TELEPHONE | D8: 60000 | E8: 4 | F8: =+'format tableau '!$D8*'format tableau '!$E8 -> 240000 | G8: =+'format tableau '!$F8*0.19 -> 45600 | H8: =+'format tableau '!$F8+'format tableau '!$G8 -> 285600
A9: pour remplacer | C9: TELEPHONE | D9: 60000 | E9: 4 | F9: =+'format tableau '!$D9*'format tableau '!$E9 -> 240000 | G9: =+'format tableau '!$F9*0.19 -> 45600 | H9: =+'format tableau '!$F9+'format tableau '!$G9 -> 285600
A10: 1- ctrl + H | C10: TELEPHONE | D10: 60000 | E10: 4 | F10: =+'format tableau '!$D10*'format tableau '!$E10 -> 240000 | G10: =+'format tableau '!$F10*0.19 -> 45600 | H10: =+'format tableau '!$F10+'format tableau '!$G10 -> 285600
C11: TELEPHONE | D11: 60000 | E11: 4 | F11: =+'format tableau '!$D11*'format tableau '!$E11 -> 240000 | G11: =+'format tableau '!$F11*0.19 -> 45600 | H11: =+'format tableau '!$F11+'format tableau '!$G11 -> 285600
C12: TELEPHONE | D12: 60000 | E12: 4 | F12: =+'format tableau '!$D12*'format tableau '!$E12 -> 240000 | G12: =+'format tableau '!$F12*0.19 -> 45600 | H12: =+'format tableau '!$F12+'format tableau '!$G12 -> 285600
C13: TELEPHONE | D13: 60000 | E13: 4 | F13: =+'format tableau '!$D13*'format tableau '!$E13 -> 240000 | G13: =+'format tableau '!$F13*0.19 -> 45600 | H13: =+'format tableau '!$F13+'format tableau '!$G13 -> 285600
C14: DELL | D14: 50000 | E14: 4 | F14: =+'format tableau '!$D14*'format tableau '!$E14 -> 200000 | G14: =+'format tableau '!$F14*0.19 -> 38000 | H14: =+'format tableau '!$F14+'format tableau '!$G14 -> 238000
C15: DELL | D15: 50000 | E15: 4 | F15: =+'format tableau '!$D15*'format tableau '!$E15 -> 200000 | G15: =+'format tableau '!$F15*0.19 -> 38000 | H15: =+'format tableau '!$F15+'format tableau '!$G15 -> 238000
C16: DELL | D16: 50000 | E16: 4 | F16: =+'format tableau '!$D16*'format tableau '!$E16 -> 200000 | G16: =+'format tableau '!$F16*0.19 -> 38000 | H16: =+'format tableau '!$F16+'format tableau '!$G16 -> 238000
C17: DELL | D17: 50000 | E17: 4 | F17: =+'format tableau '!$D17*'format tableau '!$E17 -> 200000 | G17: =+'format tableau '!$F17*0.19 -> 38000 | H17: =+'format tableau '!$F17+'format tableau '!$G17 -> 238000
C18: BUREAU | D18: 20000 | E18: 5 | F18: =+'format tableau '!$D18*'format tableau '!$E18 -> 100000 | G18: =+'format tableau '!$F18*0.19 -> 19000 | H18: =+'format tableau '!$F18+'format tableau '!$G18 -> 119000
C19: BUREAU | D19: 20000 | E19: 5 | F19: =+'format tableau '!$D19*'format tableau '!$E19 -> 100000 | G19: =+'format tableau '!$F19*0.19 -> 19000 | H19: =+'format tableau '!$F19+'format tableau '!$G19 -> 119000
C20: BUREAU | D20: 20000 | E20: 5 | F20: =+'format tableau '!$D20*'format tableau '!$E20 -> 100000 | G20: =+'format tableau '!$F20*0.19 -> 19000 | H20: =+'format tableau '!$F20+'format tableau '!$G20 -> 119000
C21: BUREAU | D21: 20000 | E21: 5 | F21: =+'format tableau '!$D21*'format tableau '!$E21 -> 100000 | G21: =+'format tableau '!$F21*0.19 -> 19000 | H21: =+'format tableau '!$F21+'format tableau '!$G21 -> 119000
C22: BUREAU | D22: 50000 | E22: 4 | F22: =+'format tableau '!$D22*'format tableau '!$E22 -> 200000 | G22: =+'format tableau '!$F22*0.19 -> 38000 | H22: =+'format tableau '!$F22+'format tableau '!$G22 -> 238000
C23: Total | H23: =SUBTOTAL(109,Tableau1[TTC]) -> 5093200

Sheet figer les cellules
B2: taux
B3: 1.1
A5: prouduit | B5: prix d'achat | C5: prix de vent | E5: produit | F5: prix d'achat | G5: 1.1 | H5: 1.15 | I5: 1.75
A6: 1 | B6: 150000 | C6: =+B6*$B$3 -> 165000 | E6: 1 | F6: 20000 | G6: =+$F6*G$5 -> 22000 | H6: =+$F6*H$5 -> 23000 | I6: =+$F6*I$5 -> 35000
A7: 2 | B7: 24000 | C7: =+B7*$B$3 -> 26400 | E7: 2 | F7: 30000 | G7: =+$F7*G$5 -> 33000 | H7: =+$F7*H$5 -> 34500 | I7: =+$F7*I$5 -> 52500
A8: 3 | B8: 50000 | C8: =+B8*$B$3 -> 55000 | E8: 3 | F8: 40000 | G8: =+$F8*G$5 -> 44000 | H8: =+$F8*H$5 -> 46000 | I8: =+$F8*I$5 -> 70000
G9: علامة الدولار قبل الحرف | H9: تثبيث العمود
G10: علامة الدولار قبل الرقم | H10: تثبيث السطر
G11: علامة الدولار قبل الرقم وقبل الحرف | H11: تثبيث العمود و السطر

Sheet suivi de caisse
B4: DIRECTION GENERALE
B5: DIRECTION FINANCES & COMPTABILITE | F5: ALGER LE : | G5: =+TODAY() -> 45310
B6: DEPARTEMENT FINANCES & COMPTABILITE
B9: N° | C9: DATE | D9: LIBELLES | E9: RECETTES | F9: DEPENSES | G9: SOLDES
B10: SOLDE AU 31/07/2022 | E10: =+G10 -> 200000 | G10: 200000
B11: =+IF(D11="","",ROW()-10) -> 1 | C11: 44894 | D11: alimentation | E11: 10000 | G11: =+G10+E11-F11 -> 210000
B12: =+IF(D12="","",ROW()-10) -> 2 | C12: 44894 | D12: gg | F12: 5000 | G12: =+G11+E12-F12 -> 205000
B13: =+IF(D13="","",ROW()-10) | C13: 44894 | F13: 50000 | G13: =+G12+E13-F13 -> 155000
B14: =+IF(D14="","",ROW()-10) | C14: 44894 | E14: 15000 | G14: =+G13+E14-F14 -> 170000
B15: =+IF(D15="","",ROW()-10) | C15: 44894 | F15: 30000 | G15: =+G14+E15-F15 -> 140000
B16: =+IF(D16="","",ROW()-10) | C16: 44894 | E16: 5000 | G16: =+G15+E16-F16 -> 145000
B17: =+IF(D17="","",ROW()-10) | C17: 44894 | G17: =+G16+E17-F17 -> 145000
B18: =+IF(D18="","",ROW()-10) | C18: 44894 | G18: =+G17+E18-F18 -> 145000
B19: =+IF(D19="","",ROW()-10) | C19: 44894 | G19: =+G18+E19-F19 -> 145000
B20: =+IF(D20="","",ROW()-10) | C20: 44894 | G20: =+G19+E20-F20 -> 145000
B21: =+IF(D21="","",ROW()-10) | C21: 44894 | G21: =+G20+E21-F21 -> 145000
B22: =+IF(D22="","",ROW()-10) | C22: 44894 | G22: =+G21+E22-F22 -> 145000
B23: TOTAL MOUVEMENT DU 01/08/2022 AU 31/08/2022 | E23: =SUM(E10:E22) -> 230000 | F23: =SUM(F10:F22) -> 85000
B24: Solde au 31/08/2022 | E24: =+E23-F23 -> 145000

Sheet PV DE CAISSE
B4: La date : | C4: =+TODAY() -> 45310
B6: la somme dans la caisse au date ,,,,,,, est un montant de : | G6: =+J16 -> 145000
B7: Biillets d'espaces | F7: Nombre | J7: Montant
B8: 2000 | F8: 25 | J8: =+B8*F8 -> 50000
B9: 1000 | F9: 80 | J9: =+B9*F9 -> 80000
B10: 500 | F10: 13 | J10: =+B10*F10 -> 6500
B11: 200 | F11: 35 | J11: =+B11*F11 -> 7000
B12: 100 | F12: 5 | J12: =+B12*F12 -> 500
B13: 50 | F13: 20 | J13: =+B13*F13 -> 1000
B14: 20 | J14: =+B14*F14 -> 0
B15: 10 | J15: =+B15*F15 -> 0
B16: Total d'espace phisique | J16: =SUM(J8:M15) -> 145000
B17: solde de caisse comptable | J17: =+'suivi de caisse'!E24 -> 145000
B18: differance | J18: =+J16-J17 -> 0
